{"book_name": "蓦然回首", "book_img": "https://img9.doubanio.com/view/subject/s/public/s34283794.jpg", "author_name": "[日本]藤本树", "press": "新星出版社", "press_year": " 2022-8", "pages": " 144", "price": " 30.00元", "ISBN": " 9787513348362", "score": " 8.8 ", "number_reviewers": "7876", "introduction": "天才漫画家藤本树（《电锯人》《炎拳》作者）"},
{"book_name": "再见绘梨", "book_img": "https://img9.doubanio.com/view/subject/s/public/s34367076.jpg", "author_name": "[日]藤本树", "press": "中信出版集团", "press_year": " 2023-1-1", "pages": " 208", "price": " 35", "ISBN": " 9787521748239", "score": " 8.8 ", "number_reviewers": "11119", "introduction": "📷只要能记起，就不怕会忘记。"},
{"book_name": "鬼滅之刃 23", "book_img": "https://img1.doubanio.com/view/subject/s/public/s33827618.jpg", "author_name": "吾峠呼世晴", "press": "鬼滅之刃", "press_year": " 2021-2", "pages": " 192", "price": " NT$100", "ISBN": " 9789572663516", "score": " 8.2 ", "number_reviewers": "1454", "introduction": "鬼的始祖‧鬼舞辻無慘與炭治郎他們的戰鬥邁入最終階段…！珠世挺身而出用在無慘身上的四種藥，讓他變得衰弱，逐漸被逼入絕境。炭治郎與禰豆子，以及鬼殺隊的命運將會如何？與鬼之間漫長的戰鬥，終於來到決勝時刻！"},
{"book_name": "虫与歌", "book_img": "https://img9.doubanio.com/view/subject/s/public/s34538444.jpg", "author_name": "[日]市川春子", "press": "上海三联书店", "press_year": " 2023-6", "pages": " 240", "price": " 45.00元", "ISBN": " 9787542680440", "score": " 8.4 ", "number_reviewers": "228", "introduction": "《虫与歌》是《宝石之国》作者市川春子的短篇漫画集，曾获手冢治虫文化奖新生奖，收录四则短篇漫画代表作及一则极短篇漫画，其中包括作者的处女作与出道作。"},
{"book_name": "乒乓", "book_img": "https://img1.doubanio.com/view/subject/s/public/s34079220.jpg", "author_name": "[日]松本大洋", "press": "广东旅游出版社", "press_year": " 2022-3", "pages": " 1032", "price": " 258.00元", "ISBN": " 9787557024444", "score": " 9.5 ", "number_reviewers": "779", "introduction": "神作参上！"},
{"book_name": "Sunny 星之子", "book_img": "https://img1.doubanio.com/view/subject/s/public/s33529469.jpg", "author_name": "[日]松本大洋", "press": "北京联合出版公司", "press_year": " 2020-2", "pages": " 1396", "price": " 298.80元", "ISBN": " 9787559633613", "score": " 9.5 ", "number_reviewers": "1989", "introduction": "天才漫画家松本大洋，倾尽全身的耀眼之作！"},
{"book_name": "西遊奇伝 大猿王 (1)", "book_img": "https://img1.doubanio.com/view/subject/s/public/s2961977.jpg", "author_name": "寺田克也", "press": "西遊奇伝 大猿王", "press_year": " 1998-12", "pages": " 99", "price": " 1,995円（税込）", "ISBN": " 9784087825756", "score": " 8.8 ", "number_reviewers": "898", "introduction": "当代きってのCG絵師、鬼才・寺田克也によって、あの『孫悟空』が斬新なアンチヒーローに生まれ変わった。「釈迦を殺す！」全編オールカラーで描かれるバーバリズムと壮麗な色彩の饗宴！"},
{"book_name": "烙印戰士 1", "book_img": "https://img1.doubanio.com/view/subject/s/public/s2601289.jpg", "author_name": "三浦建太郎", "press": "烙印戰士", "press_year": " 1994", "pages": " 223", "price": " HK$35", "ISBN": " 9789625857596", "score": " 9.4 ", "number_reviewers": "3208", "introduction": "战火纷飞的中世纪，雇佣兵团“鹰之团\"的首领格里菲斯以实力将自由战士津招至麾下。三年之后，成为格里菲斯不可或缺存在的津，对自身的存在价值产生了怀疑，决定离开“鹰之团\"寻找属于自己的理想，并将前来阻止的格里菲斯击败。深受打击的格里菲斯犯下愚蠢的过错，并为之失去了一切。变成魔物的格里菲斯将包括津在内的所有“鹰之团\"成员当成祭品献给魔物。幸存的津背负着祭品的格印走上了寻找格里菲斯的复仇之路……"},
{"book_name": "鬼滅之刃 22", "book_img": "https://img1.doubanio.com/view/subject/s/public/s33804360.jpg", "author_name": "吾峠呼世晴", "press": "鬼滅之刃", "press_year": " 2020-12", "pages": " 192", "price": " NT$100", "ISBN": " 9789572659571", "score": " 8.2 ", "number_reviewers": "864", "introduction": "距離天亮還剩一個多小時，無慘的猛攻變得更加激烈。雖然鬼殺隊僅剩的柱們緊追不捨，他們的刀有辦法砍到他嗎？還有，遭到無慘攻擊而倒下的炭治郎呢…。每個人都使出全力，這一戰將挑戰大家的極限…！"},
{"book_name": "天国大魔境 1", "book_img": "https://img1.doubanio.com/view/subject/s/public/s32299660.jpg", "author_name": "石黑正数", "press": "天国大魔境", "press_year": " 2018-7-23", "pages": " 160", "price": " JPY 748", "ISBN": " 9784065119761", "score": " 8.8 ", "number_reviewers": "796", "introduction": "美しい壁に囲まれた世界で暮らす子供たち。少年・トキオはある日、「外の外に行きたいですか?」というメッセージを受け取る。一方、外では、マルとおねえちゃんがサバイバル生活をしながら、天国を求めて、魔境となった世界を旅している。未来の日本を「あね散歩」。二つの世界を縦横無尽に行き来する、超才・石黒正数最新作、極大スケールでスタート!!"},
{"book_name": "冰菓漫画 5-6", "book_img": "https://img1.doubanio.com/view/subject/s/public/s33951138.jpg", "author_name": "[日]TASKOHNA/[日]米泽穗信/", "press": "北京工艺美术出版社", "press_year": " 2021-8", "pages": " 376", "price": " 50.00", "ISBN": " 9787514022452", "score": " 8.5 ", "number_reviewers": "41", "introduction": "折木奉太郎一行人听取了前辈们各自的推理后，认为所有人的推理都不符合编剧本乡的想法。就在他们决定放弃之时，入须学姐再次委托折木奉太郎为独立电影推理出结局。然而，当折木帮助电影推理出精彩的结局，帮助电影成功上映，最后却发现原来所有人都在不知不觉间被入须学姐利用，成为她征集剧本的工具。"},
